epdx-1.2.2.dist-info/METADATA
epdx-1.2.2.dist-info/WHEEL
epdx-1.2.2.dist-info/license_files/LICENSE
epdx-1.2.2.dist-info/license_files/LICENSE
epdx/epdx.pyi
epdx/__init__.py
epdx/pydantic.py
epdx/epdx.abi3.so
epdx-1.2.2.dist-info/RECORD
