Metadata-Version: 2.3
Name: epdx
Version: 1.2.2
Requires-Dist: pydantic >=2.0.0
Requires-Dist: mkdocs-material >=8.1.4, <9.0.0 ; extra == 'doc'
Requires-Dist: mdx-include >=1.4.1, <2.0.0 ; extra == 'doc'
Requires-Dist: datamodel-code-generator ; extra == 'codegen'
Requires-Dist: pytest ; extra == 'tests'
Requires-Dist: pytest-datafixtures ; extra == 'tests'
Provides-Extra: doc
Provides-Extra: codegen
Provides-Extra: tests
License-File: LICENSE
License-File: LICENSE
Summary: EPDx is a library for parsing EPD files into a common exchange format.
Home-Page: https://epdx.kongsgaard.eu
Author: Christian Kongsgaard <christian@kongsgaard.eu>
Author-email: Christian Kongsgaard <christian@kongsgaard.eu>
Requires-Python: >=3.10
Project-URL: homepage, https://epdx.kongsgaard.eu
Project-URL: documentation, https://epdx.kongsgaard.eu
Project-URL: repository, https://github.com/ocni-dtu/epdx
